bmi_calculator_mcp/__init__.py
bmi_calculator_mcp/__main__.py
bmi_calculator_mcp-0.1.11.dist-info/METADATA
bmi_calculator_mcp-0.1.11.dist-info/WHEEL
bmi_calculator_mcp-0.1.11.dist-info/entry_points.txt
bmi_calculator_mcp-0.1.11.dist-info/top_level.txt
bmi_calculator_mcp-0.1.11.dist-info/RECORD
