Metadata-Version: 2.4
Name: bmi-calculator-mcp
Version: 0.1.11
Summary: A Model Context Protocol server for calculating BMI (Body Mass Index)
Requires-Python: >=3.10
Requires-Dist: mcp>=1.1.2
Requires-Dist: fastmcp>=0.5.0
